objc_types_decoder/__init__.py
objc_types_decoder/__main__.py
objc_types_decoder/decode.py
objc_types_decoder-0.0.5.dist-info/LICENSE
objc_types_decoder-0.0.5.dist-info/METADATA
objc_types_decoder-0.0.5.dist-info/WHEEL
objc_types_decoder-0.0.5.dist-info/entry_points.txt
objc_types_decoder-0.0.5.dist-info/top_level.txt
objc_types_decoder-0.0.5.dist-info/RECORD
