Metadata-Version: 2.1
Name: objc-types-decoder
Version: 0.0.5
Summary: A type decoder for Objective-C types
Author-email: matan <matan1008@gmail.com>
Maintainer-email: matan <matan1008@gmail.com>
License: MIT License
Project-URL: Homepage, https://github.com/matan1008/objc-types-decoder
Project-URL: Bug Reports, https://github.com/matan1008/objc-types-decoder/issues
Keywords: ios,Objective-C
Classifier: Development Status :: 5 - Production/Stable
Classifier: License :: OSI Approved :: GNU General Public License v3 or later (GPLv3+)
Classifier: Programming Language :: Python :: 3
Classifier: Programming Language :: Python :: 3.7
Classifier: Programming Language :: Python :: 3.8
Classifier: Programming Language :: Python :: 3.9
Classifier: Programming Language :: Python :: 3.10
Classifier: Programming Language :: Python :: 3.11
Classifier: Programming Language :: Python :: 3 :: Only
Requires-Python: >=3.7
License-File: LICENSE
Provides-Extra: test
Requires-Dist: pytest ; extra == 'test'
